Metadata-Version: 1.0
Name: distributions-acp
Version: 1.0
Summary: Gaussian distributions
Home-page: UNKNOWN
Author: Andrej Cop Prek
Author-email: andrej.prek91@gmail.com
License: UNKNOWN
Platform: UNKNOWN
